<?xml version="1.0"?>
<!DOCTYPE hibernate-mapping PUBLIC "-//Hibernate/Hibernate Mapping DTD 3.0//EN"
"http://hibernate.sourceforge.net/hibernate-mapping-3.0.dtd">
<!-- Generated 06/12/2011 05:15:46 PM by Hibernate Tools 3.2.1.GA -->
<hibernate-mapping>
    <class name="datos.pojos.academico.SgaAreasConocimiento" table="SGA_AREAS_CONOCIMIENTO" schema="ACADEMICO">
        <comment>Esta tabla guarda la informaci&#195;&#179;n de las distintas &#195;&#161;reas de conocimiento a las que puede pertenecer una carrera</comment>
        <id name="id" type="int">
            <column name="ID" precision="5" scale="0" />
            <generator class="assigned" />
        </id>
        <property name="nombre" type="string">
            <column name="NOMBRE" length="50" not-null="true" unique="true">
                <comment>Nombre del area de conocimiento</comment>
            </column>
        </property>
        <property name="estaactivo" type="char">
            <column name="ESTAACTIVO" length="1" not-null="true">
                <comment>Indica si el registro est&#195;&#161; activo</comment>
            </column>
        </property>
        <property name="creado" type="string">
            <column name="CREADO" length="20" not-null="true">
                <comment>Usuario que crea el registro</comment>
            </column>
        </property>
        <property name="fechaCreacion" type="date">
            <column name="FECHA_CREACION" length="7" not-null="true">
                <comment>FEcha de creaci&#195;&#179;n del registro</comment>
            </column>
        </property>
        <property name="actualizado" type="string">
            <column name="ACTUALIZADO" length="20">
                <comment>Usuario que modifica el registro</comment>
            </column>
        </property>
        <property name="fechaActualizacion" type="date">
            <column name="FECHA_ACTUALIZACION" length="7">
                <comment>Fecha de actualizaci&#195;&#179;n del registro</comment>
            </column>
        </property>
    </class>
</hibernate-mapping>
